my_happy_jupyter_utils/__init__.py
my_happy_jupyter_utils/image_utils.py
my_happy_jupyter_utils/markdown_utils.py
my_happy_jupyter_utils/shell_utils.py
my_happy_jupyter_utils/version.py
my_happy_jupyter_utils-0.0.7.dist-info/LICENSE
my_happy_jupyter_utils-0.0.7.dist-info/METADATA
my_happy_jupyter_utils-0.0.7.dist-info/WHEEL
my_happy_jupyter_utils-0.0.7.dist-info/top_level.txt
my_happy_jupyter_utils-0.0.7.dist-info/RECORD
