Metadata-Version: 2.1
Name: my-happy-jupyter-utils
Version: 0.0.7
Summary: Jupyter utils
Home-page: https://github.com/ggservice007/my-happy-jupyter-utils
Author: ggservice007
Author-email: ggservice007@126.com
License: Apache 2
Platform: UNKNOWN
Requires-Python: >=3.7.7
Requires-Dist: requests (>=2.24.0)
